getmysql2clickhouse/__init__.py
getmysql2clickhouse-0.5.dist-info/LICENSE
getmysql2clickhouse-0.5.dist-info/METADATA
getmysql2clickhouse-0.5.dist-info/WHEEL
getmysql2clickhouse-0.5.dist-info/top_level.txt
getmysql2clickhouse-0.5.dist-info/RECORD
