Metadata-Version: 2.1
Name: getmysql2clickhouse
Version: 0.5
Summary: UNKNOWN
Home-page: https://github.com/zhihaogong25/getmysql2clickhouse
Author: Zhihao Gong
Author-email: zhihaogong25@gmail.com
License: MIT License
Platform: all
Classifier: Development Status :: 4 - Beta
Classifier: Operating System :: OS Independent
Classifier: Intended Audience :: Developers
Classifier: License :: OSI Approved :: BSD License
Classifier: Programming Language :: Python
Classifier: Programming Language :: Python :: Implementation
Classifier: Programming Language :: Python :: 2
Classifier: Programming Language :: Python :: 2.7
Classifier: Programming Language :: Python :: 3
Classifier: Programming Language :: Python :: 3.4
Classifier: Programming Language :: Python :: 3.5
Classifier: Programming Language :: Python :: 3.6
Classifier: Topic :: Software Development :: Libraries
Requires-Dist: clickhouse-driver (==0.2.0)
Requires-Dist: pymysql (==1.0.2)
Requires-Dist: psutil (==5.7.2)
